{
  "id": "broken_wheel",
  "name": "A Broken Wagon Wheel",
  "region": "forest",
  "preconditions": {
    "min_level": 5,
    "disallows_flag": "bandits_cleared"
  },
  "start_nodes": [ "start" ],
  "nodes": {
    "start": {
      "text": "You hear a loud *CRACK*! A wheel on your wagon has split, grinding you to a halt on the muddy path. What do you do?",
      "options": [
        {
          "preconditions": { "has_item": 882 },
          "text": "Attempt to repair the wheel.",
          "checks": { "survival": 15, "crafting": 10 },
          "pass": {
             "message": "repairs the wheel with a few carefully-applied braces.",
             "outcomes": [], // since a node can be reached by any number of options, this lets you add specific additional outcomes from choosing this option
             "to_node": "repair_success"
          },
          "fail": {
             "message": "tries to put a few braces on the wheel, but they fall off.",
             "outcomes": [{ "type": "lose_progress", "value": 1 }],
             "to_node": "repair_fail"
          }
        },
        {
          "text": "Search the nearby woods for a better path.",
          "checks": { "survival": 12 },
          "pass_node": "bypass_success",
          "fail_node": "bypass_fail"
        },
        {
          "text": "Abandon the wagon and continue on foot.",
          "checks": {},
          "pass": {
             "message": "repairs the wheel with a few carefully-applied braces.",
             "outcomes": [{ "type": "lose_item", "vnum": 882, "comment": "Wagon Parts" }],
             "to_node": "abandon_wagon"
          },
        }
      ]
    },
    "repair_success": {
      "text": "Using your tools and some nearby wood, you skillfully brace the wheel. It's not pretty, but it'll hold until you reach town.",
      "outcomes": [
        { "type": "add_progress", "value": 1 },
        { "type": "lose_item", "vnum": 882, "comment": "Wagon Parts" }
      ]
    },
    "repair_fail": {
      "text": "You fumble with the repair, and the wheel splinters further. You've lost valuable time.",
      "outcomes": [
        { "type": "lose_progress", "value": 1 },
        { "type": "lose_item", "vnum": 882, "comment": "Wagon Parts" }
      ]
    },
    "bypass_success": {
      "text": "You scout a narrow deer trail that bypasses the mud pit. You get around the broken wagon and back to the main path.",
      "outcomes": []
    },
    "bypass_fail": {
      "text": "You get turned around in the woods and stumble into a nest of giant spiders!",
      "outcomes": [
        { "type": "start_combat", "mobs": { "3001": 2 } }
      ],
      "pass_node": "combat_victory"
    },
    "combat_victory": {
      "text": "After a pitched battle, you stand victorious over the slain spiders. You shake the ichor from your blades and find the path.",
      "outcomes": []
    },
    "abandon_wagon": {
      "text": "Deciding it's not worth the trouble, you grab your essential gear and leave the wagon behind.",
      "outcomes": [
        { "type": "lose_item", "vnum": 881, "comment": "Wagon Deed" },
        { "type": "lose_progress", "value": 1, "comment": "Time spent transferring goods" }
      ]
    }
  }
}